.dockerignore
.gitignore
CHANGELOG.md
LICENSE
MANIFEST.in
README.md
requirements.txt
setup.py
.github/workflows/main.yml
codeart/__init__.py
codeart/client.py
codeart/colors.py
codeart/graphics.py
codeart/main.py
codeart/namer.py
codeart/nlp.py
codeart/utils.py
codeart/version.py
codeart.egg-info/PKG-INFO
codeart.egg-info/SOURCES.txt
codeart.egg-info/dependency_links.txt
codeart.egg-info/entry_points.txt
codeart.egg-info/not-zip-safe
codeart.egg-info/requires.txt
codeart.egg-info/top_level.txt
codeart/fonts/OpenSans-Regular.ttf
codeart/fonts/Pacifico-Regular.ttf
codeart/static/codeart.html
codeart/static/interactive-grid.html
codeart/static/template.html
codeart/static/tree.html
codeart/static/js/d3.v3.js
examples/codeart.png
examples/sorted.png